Metadata-Version: 2.1
Name: EAIK
Version: 1.0.0
Summary: Toolbox for Efficient Analytical Inverse Kinematics by Subproblem Decomposition.
Author-email: Daniel Ostermeier <daniel.sebastian.ostermeier@tum.de>
License:                     GNU GENERAL PUBLIC LICENSE
Project-URL: Homepage, https://github.com/OstermD/EAIK
Project-URL: Paper-Preprint, https://arxiv.org/abs/2409.14815
Keywords: Analytical Inverse Kinematics,Inverse Kinematics,Robot Kinematics
Classifier: Programming Language :: Python
Classifier: Programming Language :: Python :: 3
Classifier: Programming Language :: Python :: 3 :: Only
Requires-Python: >=3.8
License-File: LICENSE
Requires-Dist: numpy>=1.21.0
Requires-Dist: urchin>=0.0.27
Requires-Dist: setuptools
Requires-Dist: pybind11>=2.10.0
Requires-Dist: pybind11-stubgen>=0.13.0
